LICENSE.txt
MANIFEST.in
README.rst
setup.py
pycorpora/__init__.py
pycorpora.egg-info/PKG-INFO
pycorpora.egg-info/SOURCES.txt
pycorpora.egg-info/dependency_links.txt
pycorpora.egg-info/top_level.txt
pycorpora/data/pycorpora_test/test-filename.json
pycorpora/data/pycorpora_test/test.json
pycorpora/data/pycorpora_test/subdir/another_test.json