Metadata-Version: 1.1
Name: pycorpora
Version: 0.1.1
Summary: A Python wrapper for Darius Kazemi's Corpora Project
Home-page: https://github.com/aparrish/pycorpora
Author: Allison Parrish
Author-email: allison@decontextualize.com
License: LICENSE.txt
Keywords: nlp corpus text language
Platform: UNKNOWN
Classifier: Development Status :: 3 - Alpha
Classifier: Intended Audience :: Developers
Classifier: Intended Audience :: Education
Classifier: Intended Audience :: Science/Research
Classifier: License :: OSI Approved :: MIT License
Classifier: Natural Language :: English
Classifier: Topic :: Artistic Software
Classifier: Topic :: Scientific/Engineering :: Artificial Intelligence
